pyconfimporter.py
setup.py
pyconfimporter.egg-info/PKG-INFO
pyconfimporter.egg-info/SOURCES.txt
pyconfimporter.egg-info/dependency_links.txt
pyconfimporter.egg-info/requires.txt
pyconfimporter.egg-info/top_level.txt
test/test_basic.py