Metadata-Version: 1.1
Name: pyconfimporter
Version: 0.1.0
Summary: Easy way to import an external Python module into an environment.
